qualichat/__init__.py
qualichat/__main__.py
qualichat/_partials.py
qualichat/abc.py
qualichat/books.txt
qualichat/chat.py
qualichat/connector.csv
qualichat/core.py
qualichat/enums.py
qualichat/frames.py
qualichat/models.py
qualichat/regex.py
qualichat/sorters.py
qualichat/utils.py
qualichat/fonts/Roboto-Regular.ttf
qualichat-1.4.3.dist-info/LICENSE
qualichat-1.4.3.dist-info/METADATA
qualichat-1.4.3.dist-info/WHEEL
qualichat-1.4.3.dist-info/top_level.txt
qualichat-1.4.3.dist-info/RECORD
