Metadata-Version: 2.1
Name: qualichat
Version: 1.4.3
Summary: Groups' frames of relevance
Author: Erneist Manhein
License: MIT
Project-URL: Documentation, https://qualichat.readthedocs.io/en/latest/
Project-URL: Issue tracker, https://github.com/qualichat/qualichat/issues
Classifier: Development Status :: 3 - Alpha
Classifier: License :: OSI Approved :: MIT License
Classifier: Intended Audience :: Information Technology
Classifier: Natural Language :: English
Classifier: Operating System :: OS Independent
Classifier: Programming Language :: Python :: 3.9
Classifier: Programming Language :: Python :: 3.8
Classifier: Programming Language :: Python :: 3.7
Classifier: Topic :: Internet
Classifier: Topic :: Software Development :: Libraries
Classifier: Topic :: Utilities
Requires-Python: >=3.7.1
License-File: LICENSE
Requires-Dist: spacy
Requires-Dist: plotly
Requires-Dist: emojis
Requires-Dist: pandas
Requires-Dist: wordcloud
Requires-Dist: matplotlib
Requires-Dist: tldextract
Requires-Dist: questionary
Requires-Dist: rich
Requires-Dist: qualichat-qualitube
Requires-Dist: deep-translator
Requires-Dist: spacytextblob
